monpa/__init__.py
monpa/changelog.md
monpa/configuration_albert.py
monpa/crf_layer.py
monpa/modeling_albert.py
monpa/pos.tgt.dict
monpa/tokenization.py
monpa/vocab_monpa.vocab
monpa/albert_config/albert_config_mo.json
monpa/model/monpa_model_8000.pt
monpa/utils/__init__.py
monpa-0.3.3.dist-info/LICENSE
monpa-0.3.3.dist-info/METADATA
monpa-0.3.3.dist-info/WHEEL
monpa-0.3.3.dist-info/top_level.txt
monpa-0.3.3.dist-info/RECORD
