Metadata-Version: 2.1
Name: monpa
Version: 0.3.3
Summary: MONPA is an end-to-end model to jointly conduct Chinese word segmentation, POS and NE labeling
Home-page: https://github.com/monpa-team/monpa
Author: MONPA team: TMU NLPLAB
Author-email: monpa.cut@gmail.com
License: UNKNOWN
Platform: UNKNOWN
Classifier: Programming Language :: Python :: 3
Classifier: License :: Free for non-commercial use
Classifier: Operating System :: OS Independent
Requires-Python: >=3.6
License-File: LICENSE
Requires-Dist: torch (>=1.0)
Requires-Dist: requests
